{
  "bookingCode": "DCBEDC97-BE21-4059-8FEF-748FA324B6EA",
  "plate": "51A-123.45",
  "parking": "Vincom Center Parking",
  "slot": "B1 - Zone V1 - V1-17",
  "slotId": "V1-17",
  "floor": "B1",
  "zone": "V1",
  "zoneUUID": "dd657628-ec4c-4772-83e0-f9b9a85e623d",
  "package": "Theo tháng",
  "startDate": "05/04/2026",
  "total": "960000",
  "status": "Chờ thanh toán",
  "qrFile": "booking_qr_DCBEDC97.svg",
  "notes": [
    "Dùng bookingCode để simulate check-in tại gate trong Unity",
    "Xe biển số 51A-123.45 (VinFast VF8 Plus 2024) tiến vào gate",
    "Gate camera đọc biển số → gọi check-in API → hệ thống xác nhận slot V1-17",
    "Xe di chuyển đến slot V1-17 ở tầng B1, khu V1",
    "AI camera f1-overview (y=35) theo dõi và detect xe tại slot"
  ]
}
